{
  "trump clashes with fed chair over renovation costs": null,
  "presses": {
    "src": "https://live.staticflickr.com/4129/5178769981_65cee40aac_b.jpg",
    "thumbnail": "https://api.openverse.org/v1/images/bf02669d-d42f-4a66-a324-06a0e16cdd76/thumb/",
    "alt": "Facebook Press Conference",
    "credit": "Robert Scoble / CC BY 2.0",
    "license": "by",
    "license_version": "2.0",
    "license_url": "https://creativecommons.org/licenses/by/2.0/",
    "provider": "flickr",
    "source": "Openverse"
  },
  "france": {
    "src": "https://live.staticflickr.com/2050/2114358622_23b460f2f2_b.jpg",
    "thumbnail": "https://api.openverse.org/v1/images/2edf8c99-3e6b-4c18-b03e-8b86001d7977/thumb/",
    "alt": "France",
    "credit": "Greg Walters / CC BY 2.0",
    "license": "by",
    "license_version": "2.0",
    "license_url": "https://creativecommons.org/licenses/by/2.0/",
    "provider": "flickr",
    "source": "Openverse"
  },
  "canada": {
    "src": "https://live.staticflickr.com/520/30765139183_62bb4e4667_b.jpg",
    "thumbnail": "https://api.openverse.org/v1/images/dccf4c8d-0b91-43f7-8362-3fc6207ad07d/thumb/",
    "alt": "canada",
    "credit": "PokemonaDeChroma / CC BY 2.0",
    "license": "by",
    "license_version": "2.0",
    "license_url": "https://creativecommons.org/licenses/by/2.0/",
    "provider": "flickr",
    "source": "Openverse"
  },
  "deputy ag meets ghislaine maxwell amid epstein document demands deputy attorney general todd blanche": null,
  "ghislaine maxwell": {
    "src": "https://live.staticflickr.com/65535/48505517097_f3e1879e81_b.jpg",
    "thumbnail": "https://api.openverse.org/v1/images/89e7c39d-7aa2-4963-8d05-d59b8f2e02a3/thumb/",
    "alt": "Ghislaine Maxwell",
    "credit": "trendingtopics / CC BY 2.0",
    "license": "by",
    "license_version": "2.0",
    "license_url": "https://creativecommons.org/licenses/by/2.0/",
    "provider": "flickr",
    "source": "Openverse"
  },
  "wrestling legend hulk hogan dies": null,
  "cardiac arrest hulk hogan": null,
  "his": {
    "src": "https://live.staticflickr.com/8357/8405954250_b389c295c1_b.jpg",
    "thumbnail": "https://api.openverse.org/v1/images/2351f2f8-9f13-4b3e-a11c-696a7707705f/thumb/",
    "alt": "Barefoot Karateka Boy Marc in his karate suit shows his soles",
    "credit": "footboymarc / CC BY 2.0",
    "license": "by",
    "license_version": "2.0",
    "license_url": "https://creativecommons.org/licenses/by/2.0/",
    "provider": "flickr",
    "source": "Openverse"
  },
  "angara airlines plane crashes": null,
  "russia": {
    "src": "https://live.staticflickr.com/5589/15147968852_3f9aa97d20_b.jpg",
    "thumbnail": "https://api.openverse.org/v1/images/6d73b4de-e43e-44cd-afdc-e561e58e8ee0/thumb/",
    "alt": "Staraya Russa, Russia",
    "credit": "Lex Kravetski / CC BY 2.0",
    "license": "by",
    "license_version": "2.0",
    "license_url": "https://creativecommons.org/licenses/by/2.0/",
    "provider": "flickr",
    "source": "Openverse"
  },
  "astronomer executives resign after public incident": null,
  "concert astronomer": {
    "src": "https://live.staticflickr.com/3455/3290814376_ed119cc482_b.jpg",
    "thumbnail": "https://api.openverse.org/v1/images/56de7fb7-0efb-4527-9ec7-983facb3e2d3/thumb/",
    "alt": "------Prague Astronomical Clock-----",
    "credit": "digital deadhead / CC BY 2.0",
    "license": "by",
    "license_version": "2.0",
    "license_url": "https://creativecommons.org/licenses/by/2.0/",
    "provider": "flickr",
    "source": "Openverse"
  },
  "thailand": {
    "src": "https://live.staticflickr.com/8524/8673912663_c18e4f0d16_b.jpg",
    "thumbnail": "https://api.openverse.org/v1/images/4171d071-f855-496c-be9d-26640f69ca1d/thumb/",
    "alt": "Pattaya Thailand",
    "credit": "newhotelus / CC BY 2.0",
    "license": "by",
    "license_version": "2.0",
    "license_url": "https://creativecommons.org/licenses/by/2.0/",
    "provider": "flickr",
    "source": "Openverse"
  },
  "von miller": {
    "src": "https://live.staticflickr.com/2598/3953523637_8a643a1f14_b.jpg",
    "thumbnail": "https://api.openverse.org/v1/images/e978ced2-e53b-42c4-8bb8-a69f4c15f629/thumb/",
    "alt": "Oskar von Miller Forum",
    "credit": "digital cat \uf8ff / CC BY 2.0",
    "license": "by",
    "license_version": "2.0",
    "license_url": "https://creativecommons.org/licenses/by/2.0/",
    "provider": "flickr",
    "source": "Openverse"
  },
  "trump administration criticized": {
    "src": "https://live.staticflickr.com/4657/40170487061_8477f01597_b.jpg",
    "thumbnail": "https://api.openverse.org/v1/images/acd5b9ab-54a9-4879-9607-54592ad55736/thumb/",
    "alt": "The United States and Mexico in the Trump Era",
    "credit": "InterAmericanDialogue / CC BY 2.0",
    "license": "by",
    "license_version": "2.0",
    "license_url": "https://creativecommons.org/licenses/by/2.0/",
    "provider": "flickr",
    "source": "Openverse"
  },
  "how": {
    "src": "https://live.staticflickr.com/7302/12572168315_e61f78a8c8_b.jpg",
    "thumbnail": "https://api.openverse.org/v1/images/010c2f29-9f3e-4182-af36-376e6b1e44da/thumb/",
    "alt": "How To Make A Cyanotype Pt. 1 - 'THE STUFF'",
    "credit": "_-0-_ / CC BY 2.0",
    "license": "by",
    "license_version": "2.0",
    "license_url": "https://creativecommons.org/licenses/by/2.0/",
    "provider": "flickr",
    "source": "Openverse"
  },
  "hulk hogan": {
    "src": "https://live.staticflickr.com/8328/8126534293_10f6c526c8.jpg",
    "thumbnail": "https://api.openverse.org/v1/images/17bfa79c-c822-4623-86b6-a40eb430eebb/thumb/",
    "alt": "Hulk Hogan Cat",
    "credit": "Petful.com / CC BY 2.0",
    "license": "by",
    "license_version": "2.0",
    "license_url": "https://creativecommons.org/licenses/by/2.0/",
    "provider": "flickr",
    "source": "Openverse"
  },
  "google": {
    "src": "https://live.staticflickr.com/65535/51719942029_08959744a2_b.jpg",
    "thumbnail": "https://api.openverse.org/v1/images/dffb9d2f-9828-4636-947d-25302b16f3d2/thumb/",
    "alt": "Google",
    "credit": "Web Summit / CC BY 2.0",
    "license": "by",
    "license_version": "2.0",
    "license_url": "https://creativecommons.org/licenses/by/2.0/",
    "provider": "flickr",
    "source": "Openverse"
  },
  "trump directs cabinet": null,
  "preserve college sports": {
    "src": "https://live.staticflickr.com/2050/1947573470_ae9233c3a5_b.jpg",
    "thumbnail": "https://api.openverse.org/v1/images/7f0f1c8a-4d60-4923-b7dd-0ec4c80260c5/thumb/",
    "alt": "Dr. Charles Richard Drew",
    "credit": "dbking / CC BY 2.0",
    "license": "by",
    "license_version": "2.0",
    "license_url": "https://creativecommons.org/licenses/by/2.0/",
    "provider": "flickr",
    "source": "Openverse"
  },
  "british medical association plans": null,
  "day strike starting friday the british medical association": null,
  "friday": {
    "src": "https://live.staticflickr.com/574/23520725280_81bc08d2b6_b.jpg",
    "thumbnail": "https://api.openverse.org/v1/images/607a000c-e49d-4e12-82b6-d3afb8815a43/thumb/",
    "alt": "Flickr Friday: Christmas Traditions",
    "credit": "Flickr / CC BY 2.0",
    "license": "by",
    "license_version": "2.0",
    "license_url": "https://creativecommons.org/licenses/by/2.0/",
    "provider": "flickr",
    "source": "Openverse"
  },
  "comprehensive nfl training camp coverage": null,
  "team": {
    "src": "https://live.staticflickr.com/1250/5136655861_6cc1f50ede_b.jpg",
    "thumbnail": "https://api.openverse.org/v1/images/d7d9adef-5ced-47a6-bf9d-e96f596e9cbd/thumb/",
    "alt": "Team",
    "credit": "Phillie Casablanca / CC BY 2.0",
    "license": "by",
    "license_version": "2.0",
    "license_url": "https://creativecommons.org/licenses/by/2.0/",
    "provider": "flickr",
    "source": "Openverse"
  },
  "quantum computers outperform classical ones": {
    "src": "https://live.staticflickr.com/8141/6971396150_42957cf558_b.jpg",
    "thumbnail": "https://api.openverse.org/v1/images/60a05c82-fa10-442d-bd38-1e27ece11488/thumb/",
    "alt": "Plucking the Strings of the Multiverse",
    "credit": "jurvetson / CC BY 2.0",
    "license": "by",
    "license_version": "2.0",
    "license_url": "https://creativecommons.org/licenses/by/2.0/",
    "provider": "flickr",
    "source": "Openverse"
  },
  "trump mulls ending capital": null,
  "gains tax": {
    "src": "https://live.staticflickr.com/65535/49111352088_8749a27f99.jpg",
    "thumbnail": "https://api.openverse.org/v1/images/0ee54871-9e40-42f9-9a93-d0ef7177a2b4/thumb/",
    "alt": "IRS Schedule D Tax Software for Stock Traders and Investors. Capital Gains Tax Tool. Import Trades. Export to Popular Tax Return Software. Windows PC or Laptop.",
    "credit": "",
    "license": "cc0",
    "license_version": "1.0",
    "license_url": "https://creativecommons.org/publicdomain/zero/1.0/",
    "provider": "flickr",
    "source": "Openverse"
  },
  "uk study": null,
  "pandemic lockdowns may have sped up mental aging": null,
  "uk": {
    "src": "https://live.staticflickr.com/1595/26246679326_6336ec5f1c_b.jpg",
    "thumbnail": "https://api.openverse.org/v1/images/3e56d481-a95f-462f-9908-0ba68325aa86/thumb/",
    "alt": "Reading, UK",
    "credit": "VV Nincic / CC BY 2.0",
    "license": "by",
    "license_version": "2.0",
    "license_url": "https://creativecommons.org/licenses/by/2.0/",
    "provider": "flickr",
    "source": "Openverse"
  },
  "shanghai hosts major ai summit": null,
  "propel china": {
    "src": "https://live.staticflickr.com/2664/4109578069_a32e12d7b5_b.jpg",
    "thumbnail": "https://api.openverse.org/v1/images/a513476d-c310-4d35-bcd7-a36af6a185a1/thumb/",
    "alt": "Atavistic Beacon",
    "credit": "jurvetson / CC BY 2.0",
    "license": "by",
    "license_version": "2.0",
    "license_url": "https://creativecommons.org/licenses/by/2.0/",
    "provider": "flickr",
    "source": "Openverse"
  },
  "new aluminum": {
    "src": "https://live.staticflickr.com/7421/27973273926_d1af502c9a_b.jpg",
    "thumbnail": "https://api.openverse.org/v1/images/6316b1b7-9fd2-4288-93e8-c543944963c7/thumb/",
    "alt": "New Aluminum Capacitors With Increased Vibration Resistance to 50 g Deliver Stability and Reliability for Automotive and Industrial Applications",
    "credit": "Vishay Intertechnology / CC BY 2.0",
    "license": "by",
    "license_version": "2.0",
    "license_url": "https://creativecommons.org/licenses/by/2.0/",
    "provider": "flickr",
    "source": "Openverse"
  },
  "senegal signs artemis accords": null,
  "space exploration": {
    "src": "https://live.staticflickr.com/2538/4014786221_f8c7c81d58_b.jpg",
    "thumbnail": "https://api.openverse.org/v1/images/6c5020c4-8c3f-4e14-a2d3-07361dc4461a/thumb/",
    "alt": "Deep Space Explorer #1",
    "credit": "",
    "license": "cc0",
    "license_version": "1.0",
    "license_url": "https://creativecommons.org/publicdomain/zero/1.0/",
    "provider": "flickr",
    "source": "Openverse"
  },
  "neutrinos may self": null,
  "interact": {
    "src": "https://live.staticflickr.com/1252/5097547405_6701529706_b.jpg",
    "thumbnail": "https://api.openverse.org/v1/images/9cdc3f8d-d77f-4359-b3b6-056e6146e907/thumb/",
    "alt": "Data Represented in an Interactive 3-D Form",
    "credit": "Idaho National Laboratory / CC BY 2.0",
    "license": "by",
    "license_version": "2.0",
    "license_url": "https://creativecommons.org/licenses/by/2.0/",
    "provider": "flickr",
    "source": "Openverse"
  },
  "paramount": {
    "src": "https://live.staticflickr.com/3263/2772989178_82ea5f9fd1_b.jpg",
    "thumbnail": "https://api.openverse.org/v1/images/da272daa-9a56-4520-b064-97d53563942c/thumb/",
    "alt": "Paramount Theatre, Oakland, CA",
    "credit": "BWChicago / CC BY 2.0",
    "license": "by",
    "license_version": "2.0",
    "license_url": "https://creativecommons.org/licenses/by/2.0/",
    "provider": "flickr",
    "source": "Openverse"
  },
  "american airlines": {
    "src": "https://live.staticflickr.com/8155/7417125618_f6a9fc41de_b.jpg",
    "thumbnail": "https://api.openverse.org/v1/images/76963183-e7f2-490e-9785-2acc384e08d8/thumb/",
    "alt": "American Airlines 737 Airplane Photo i002 by Grant Wickes",
    "credit": "Grant Wickes / CC BY 2.0",
    "license": "by",
    "license_version": "2.0",
    "license_url": "https://creativecommons.org/licenses/by/2.0/",
    "provider": "flickr",
    "source": "Openverse"
  },
  "firms battle": {
    "src": "https://live.staticflickr.com/6173/6173049640_0ede3ba4e0_b.jpg",
    "thumbnail": "https://api.openverse.org/v1/images/968e504b-0edd-41a3-b434-af96e322534b/thumb/",
    "alt": "Proper Hygiene",
    "credit": "The U.S. Army / CC BY 2.0",
    "license": "by",
    "license_version": "2.0",
    "license_url": "https://creativecommons.org/licenses/by/2.0/",
    "provider": "flickr",
    "source": "Openverse"
  },
  "world court": {
    "src": "https://upload.wikimedia.org/wikipedia/commons/1/15/Hilary_Christiane_Mary_Charlesworth_%28born_1955%29_giving_the_lecture_Assessing_International_Adjudication_%E2%80%93_The_World_Court_at_100.png",
    "thumbnail": "https://api.openverse.org/v1/images/3a24ddaf-4553-4af0-8199-ef08afee9b7f/thumb/",
    "alt": "Hilary Christiane Mary Charlesworth (born 1955) giving the lecture Assessing International Adjudication \u2013 The World Court at 100",
    "credit": "ANU TV / CC BY 3.0",
    "license": "by",
    "license_version": "3.0",
    "license_url": "https://creativecommons.org/licenses/by/3.0/",
    "provider": "wikimedia",
    "source": "Openverse"
  },
  "nvidia ai": {
    "src": "https://live.staticflickr.com/5767/30796823531_85932ecaa0_b.jpg",
    "thumbnail": "https://api.openverse.org/v1/images/183e9fc4-7118-4ee4-bd8c-4589c43f5008/thumb/",
    "alt": "Jen-Hsun Huang, CEO of NVIDIA, carrying the torch for Moore\u2019s Law",
    "credit": "jurvetson / CC BY 2.0",
    "license": "by",
    "license_version": "2.0",
    "license_url": "https://creativecommons.org/licenses/by/2.0/",
    "provider": "flickr",
    "source": "Openverse"
  },
  "villarreal nears": {
    "src": "https://live.staticflickr.com/7168/6507064975_6e36e7eb0f_b.jpg",
    "thumbnail": "https://api.openverse.org/v1/images/fc67f5c6-cb31-426e-9682-222235f923f8/thumb/",
    "alt": "20100408-NRCS-JMV-0001",
    "credit": "USDAgov / CC BY 2.0",
    "license": "by",
    "license_version": "2.0",
    "license_url": "https://creativecommons.org/licenses/by/2.0/",
    "provider": "flickr",
    "source": "Openverse"
  },
  "two": {
    "src": "https://live.staticflickr.com/1306/4679199010_29e9b08a14.jpg",
    "thumbnail": "https://api.openverse.org/v1/images/946dd2be-dd42-41c9-b32f-d8abb5300a9b/thumb/",
    "alt": "Two female laboratory workers test synthetic rubber in the Polymer Rubber Corporation plant. / \u00c0 la Soci\u00e9t\u00e9 Polymer Limit\u00e9e, deux employ\u00e9es font des essais sur du caoutchouc synth\u00e9tique",
    "credit": "BiblioArchives / LibraryArchives / CC BY 2.0",
    "license": "by",
    "license_version": "2.0",
    "license_url": "https://creativecommons.org/licenses/by/2.0/",
    "provider": "flickr",
    "source": "Openverse"
  },
  "vc victor lazarte": null,
  "benchmark": {
    "src": "https://live.staticflickr.com/2853/9819156864_6f3a4ae0c0_b.jpg",
    "thumbnail": "https://api.openverse.org/v1/images/a8687577-f81f-429f-967e-256e38d5595c/thumb/",
    "alt": "Gold-standard Benchmark for Sustainable Business Workshop",
    "credit": "The Natural Step Canada / CC BY 2.0",
    "license": "by",
    "license_version": "2.0",
    "license_url": "https://creativecommons.org/licenses/by/2.0/",
    "provider": "flickr",
    "source": "Openverse"
  },
  "espn survey gauges nba rookie class": null,
  "roy predictions espn": null,
  "jeremy woo": {
    "src": "https://live.staticflickr.com/5303/5574673316_fdf746d0a7_b.jpg",
    "thumbnail": "https://api.openverse.org/v1/images/f76eaf63-7d06-49a5-bac3-6cd8f1123160/thumb/",
    "alt": "Eaglebrook School Archives, 1990s",
    "credit": "EaglebrookSchool / CC BY 2.0",
    "license": "by",
    "license_version": "2.0",
    "license_url": "https://creativecommons.org/licenses/by/2.0/",
    "provider": "flickr",
    "source": "Openverse"
  },
  "adirondack hiking trail closed due": null,
  "moose concerns new york": null,
  "adirondack": {
    "src": "https://live.staticflickr.com/8455/8026530848_b07a38aaa8_b.jpg",
    "thumbnail": "https://api.openverse.org/v1/images/b988d90e-d7f9-4632-85bc-38168b211e4d/thumb/",
    "alt": "Adirondack Balloon Fest 2012",
    "credit": "Traj- / CC BY 2.0",
    "license": "by",
    "license_version": "2.0",
    "license_url": "https://creativecommons.org/licenses/by/2.0/",
    "provider": "flickr",
    "source": "Openverse"
  },
  "ekitike joins liverpool": null,
  "deal worth over": {
    "src": "https://live.staticflickr.com/2430/3977734482_01c770cfc9.jpg",
    "thumbnail": "https://api.openverse.org/v1/images/e05bf610-2557-4173-b6da-29a1fe56c293/thumb/",
    "alt": "target $5.45",
    "credit": "EvelynGiggles / CC BY 2.0",
    "license": "by",
    "license_version": "2.0",
    "license_url": "https://creativecommons.org/licenses/by/2.0/",
    "provider": "flickr",
    "source": "Openverse"
  },
  "adam svensson sets course record": null,
  "under": {
    "src": "https://live.staticflickr.com/2754/4346024348_d3cd45eee9.jpg",
    "thumbnail": "https://api.openverse.org/v1/images/6a20d6ef-77fe-4cea-94a0-68e9fc36c6e1/thumb/",
    "alt": "Heart - photo used under Creative Commons Licence",
    "credit": "USW-UniLife / CC BY 2.0",
    "license": "by",
    "license_version": "2.0",
    "license_url": "https://creativecommons.org/licenses/by/2.0/",
    "provider": "flickr",
    "source": "Openverse"
  },
  "starlink": {
    "src": "https://live.staticflickr.com/65535/47926209216_ee21a9b58a_b.jpg",
    "thumbnail": "https://api.openverse.org/v1/images/4ae71520-eb3c-4ab5-8a41-6bb13f449342/thumb/",
    "alt": "SpaceX Starlink Broadband Satellite Deployment over Earth",
    "credit": "jurvetson / CC BY 2.0",
    "license": "by",
    "license_version": "2.0",
    "license_url": "https://creativecommons.org/licenses/by/2.0/",
    "provider": "flickr",
    "source": "Openverse"
  },
  "blue jays face al central": null,
  "leading tigers": {
    "src": "https://live.staticflickr.com/7060/6820565620_aac34f2787_b.jpg",
    "thumbnail": "https://api.openverse.org/v1/images/df762988-397d-48c3-a338-bdeae7715adb/thumb/",
    "alt": "Forest dream!",
    "credit": "VinothChandar / CC BY 2.0",
    "license": "by",
    "license_version": "2.0",
    "license_url": "https://creativecommons.org/licenses/by/2.0/",
    "provider": "flickr",
    "source": "Openverse"
  },
  "meme stock traders target gopro": null,
  "krispy kreme": {
    "src": "https://live.staticflickr.com/185/392221718_9e66d89ca7_b.jpg",
    "thumbnail": "https://api.openverse.org/v1/images/4f7a92fd-c6af-40a5-bbee-97a3097ce73c/thumb/",
    "alt": "Bacon Krispy Kreme burger",
    "credit": "satanslaundromat / CC BY 2.0",
    "license": "by",
    "license_version": "2.0",
    "license_url": "https://creativecommons.org/licenses/by/2.0/",
    "provider": "flickr",
    "source": "Openverse"
  }
}