{
  "fetched": 3069,
  "filtered": 1220,
  "clustered": 114,
  "scored": 30,
  "feeds": {
    "feeds_total": 71,
    "url_normalized": 12,
    "url_rejected": 0,
    "proxy_usage": {
      "direct": 68
    },
    "feed_failures": {
      "goosefeed.com": 12,
      "r.jina.ai": 12,
      "rsshub.app": 2,
      "www.nasa.gov": 2,
      "feeds.reuters.com": 1,
      "english.alarabiya.net": 1,
      "www.nature.com": 1,
      "www.investopedia.com": 1,
      "www.theglobeandmail.com": 1,
      "rss.sciam.com": 1,
      "as.com": 1,
      "www.tsn.ca": 1
    }
  },
  "cache_metrics": {
    "summary": {
      "load_ms": 64,
      "miss": 30
    },
    "constructiveness": {
      "miss": 45
    },
    "headline": {
      "miss": 30
    }
  },
  "clustering_metrics": {
    "counters": {
      "articles_before_dedupe": 1220,
      "articles_in": 1203,
      "candidate_clusters_checked_total": 596678,
      "candidate_articles_checked_total": 723003,
      "similarity_calls_total": 5581361,
      "clusters_out_pre_merge": 975,
      "merge_iterations_pass1": 14,
      "merge_iterations_pass2": 19,
      "clusters_out_final": 942
    },
    "dedupe": {
      "removed_count": 17,
      "reason_counts": {
        "canonical_url": 17
      },
      "articles_in": 1220,
      "articles_after": 1203
    },
    "timings": {
      "clustering_assign": 1325.0210001543164,
      "clustering_merge_pass1": 9025.693339703605,
      "clustering_merge_pass2": 23.49996012263,
      "clustering_finalize": 0.3924380512908101,
      "clustering_total": 10374.607544695027
    },
    "cluster_size_stats": {
      "min": 1,
      "p50": 1.0,
      "p90": 2.0,
      "p99": 7.0,
      "max": 13
    },
    "candidates_per_article": {
      "avg": 495.99168744804655,
      "p90": 869.0,
      "p99": 963.98
    }
  },
  "gpt": {
    "gpt_final_story_count": 30,
    "gpt_calls_total": 30,
    "gpt_cache_hits": 0,
    "gpt_cache_misses": 30,
    "gpt_combined_calls": 30,
    "gpt_input_char_count_total": 16236
  },
  "headline_metrics": {
    "total": 30,
    "missing": 0,
    "source_counts": {
      "gpt": 30
    },
    "length": {
      "avg": 54.03,
      "median": 54.5,
      "max": 67,
      "over_limit": 0
    },
    "uniqueness": {
      "unique_titles": 30,
      "duplicate_groups": 0,
      "repeated_titles": 0,
      "deduped_ratio": 1.0
    },
    "punctuation_flags": {
      "contains_separator": 0
    }
  }
}